infi.pysync-0.0.16-py2.7-nspkg.pth
infi/pysync/__init__.py
infi/pysync/__version__.py
infi/pysync/pathmatch.py
infi/pysync/sftp.py
infi.pysync-0.0.16.dist-info/LICENSE
infi.pysync-0.0.16.dist-info/METADATA
infi.pysync-0.0.16.dist-info/WHEEL
infi.pysync-0.0.16.dist-info/entry_points.txt
infi.pysync-0.0.16.dist-info/namespace_packages.txt
infi.pysync-0.0.16.dist-info/top_level.txt
infi.pysync-0.0.16.dist-info/RECORD
